junosviz/__init__.py
junosviz/bgp_jnxBgpM2PeerInTotalMessages/__init__.py
junosviz/bgp_jnxBgpM2PeerInTotalMessages/bgp_peer_InTotal_Messages.py
junosviz/bgp_jnxBgpM2PeerState_alert/__init__.py
junosviz/bgp_jnxBgpM2PeerState_alert/bgp_peer_state_monitor.py
junosviz/bgp_jnxBgpM2PeerState_alert/bgp_peer_state_monitor_resolve.py
junosviz/bgp_jnxBgpM2PrefixInPrefixesAccepted_alert/__init__.py
junosviz/bgp_jnxBgpM2PrefixInPrefixesAccepted_alert/bgp_peer_accept_prefixes.py
junosviz/bgp_monitoring/__init__.py
junosviz/bgp_monitoring/bgp_jnxBgpM2PeerInTotalMessages/__init__.py
junosviz/bgp_monitoring/bgp_jnxBgpM2PeerInTotalMessages/bgp_peer_InTotal_Messages.py
junosviz/bgp_monitoring/bgp_jnxBgpM2PeerState_alert/__init__.py
junosviz/bgp_monitoring/bgp_jnxBgpM2PeerState_alert/bgp_peer_state_monitor.py
junosviz/bgp_monitoring/bgp_jnxBgpM2PeerState_alert/bgp_peer_state_monitor_resolve.py
junosviz/bgp_monitoring/bgp_jnxBgpM2PrefixInPrefixesAccepted_alert/__init__.py
junosviz/bgp_monitoring/bgp_jnxBgpM2PrefixInPrefixesAccepted_alert/bgp_peer_accept_prefixes.py
junosviz/bgp_monitoring/bgp_predict/__init__.py
junosviz/bgp_monitoring/bgp_predict/jnx_lstm.py
junosviz/bgp_monitoring/bgp_predict/jnx_prophet.py
junosviz/bgp_monitoring/bogon_cymru/__init__.py
junosviz/bgp_monitoring/bogon_cymru/jnx_cymru_bogon.py
junosviz/bgp_monitoring/junx_components/__init__.py
junosviz/bgp_monitoring/junx_components/jnx_componentstate.py
junosviz/bgp_monitoring/yang_jnxbgp_peer_stateinfo/__init__.py
junosviz/bgp_monitoring/yang_jnxbgp_peer_stateinfo/yang_bgp_peer_info.py
junosviz/bgp_predict/__init__.py
junosviz/bgp_predict/jnx_lstm.py
junosviz/bgp_predict/jnx_prophet.py
junosviz/bogon_cymru/__init__.py
junosviz/bogon_cymru/jnx_cymru_bogon.py
junosviz/junx_components/__init__.py
junosviz/junx_components/jnx_componentstate.py
junosviz/yang_jnxbgp_peer_stateinfo/__init__.py
junosviz/yang_jnxbgp_peer_stateinfo/yang_bgp_peer_info.py
junosviz-1.1.0.dist-info/LICENSE
junosviz-1.1.0.dist-info/METADATA
junosviz-1.1.0.dist-info/WHEEL
junosviz-1.1.0.dist-info/top_level.txt
junosviz-1.1.0.dist-info/RECORD
