Metadata-Version: 2.2
Name: junosviz
Version: 1.1.0
Summary: A Python package for BGP monitoring,state analysis and prediction.
Author-email: Menuka Wijayarathne <menu.sri13@gmail.com>
License: MIT
Project-URL: Homepage, https://github.com/Menuka-Wijayarathne/junosviz
Project-URL: Documentation, https://github.com/Menuka-Wijayarathne/junosviz/wiki
Project-URL: Release, https://github.com/Menuka-Wijayarathne/junosviz/releases/tag/v1.1.0
Classifier: Programming Language :: Python :: 3
Classifier: License :: OSI Approved :: MIT License
Classifier: Operating System :: OS Independent
Requires-Python: >=3.12
License-File: LICENSE
Requires-Dist: aiohttp
Requires-Dist: httpx
Requires-Dist: nornir
Requires-Dist: ncclient
Requires-Dist: pysnmp
Requires-Dist: pandas
Requires-Dist: matplotlib
Requires-Dist: scikit-learn
Requires-Dist: tensorflow
Requires-Dist: influxdb-client
Requires-Dist: flask
